odoo/addons/base_group_backend/README.rst
odoo/addons/base_group_backend/__init__.py
odoo/addons/base_group_backend/__manifest__.py
odoo/addons/base_group_backend/data/res_groups.xml
odoo/addons/base_group_backend/demo/__init__.py
odoo/addons/base_group_backend/demo/backend_dummy_model.py
odoo/addons/base_group_backend/demo/backend_dummy_model.xml
odoo/addons/base_group_backend/demo/ir.model.access.csv
odoo/addons/base_group_backend/demo/res_partners.xml
odoo/addons/base_group_backend/demo/res_users.xml
odoo/addons/base_group_backend/demo/test-model.xml
odoo/addons/base_group_backend/i18n/base_group_backend.pot
odoo/addons/base_group_backend/i18n/it.po
odoo/addons/base_group_backend/models/__init__.py
odoo/addons/base_group_backend/models/ir_ui_menu.py
odoo/addons/base_group_backend/models/res_users.py
odoo/addons/base_group_backend/readme/CONFIGURE.rst
odoo/addons/base_group_backend/readme/CONTRIBUTORS.rst
odoo/addons/base_group_backend/readme/DESCRIPTION.rst
odoo/addons/base_group_backend/readme/USAGE.rst
odoo/addons/base_group_backend/security/ir.model.access.csv
odoo/addons/base_group_backend/static/description/backend_ui.png
odoo/addons/base_group_backend/static/description/dummy_app.png
odoo/addons/base_group_backend/static/description/icon.png
odoo/addons/base_group_backend/static/description/index.html
odoo/addons/base_group_backend/tests/__init__.py
odoo/addons/base_group_backend/tests/test_module.py
odoo_addon_base_group_backend-16.0.1.1.0.2.dist-info/METADATA
odoo_addon_base_group_backend-16.0.1.1.0.2.dist-info/WHEEL
odoo_addon_base_group_backend-16.0.1.1.0.2.dist-info/top_level.txt
odoo_addon_base_group_backend-16.0.1.1.0.2.dist-info/RECORD
