Metadata-Version: 2.1
Name: odoo-addon-base_group_backend
Version: 16.0.1.1.0.2
Summary: Group backend
Home-page: https://github.com/OCA/server-backend
Author: Pierre Verkest, Odoo Community Association (OCA)
Author-email: support@odoo-community.org
License: LGPL-3
Classifier: Programming Language :: Python
Classifier: Framework :: Odoo
Classifier: Framework :: Odoo :: 16.0
Classifier: License :: OSI Approved :: GNU Lesser General Public License v3 (LGPLv3)
Classifier: Development Status :: 3 - Alpha
Requires-Python: >=3.10
Requires-Dist: odoo<16.1dev,>=16.0a
